{
  "id": "case-301",
  "level": 3,
  "title": "Тестирование проводилось на другой сборке",
  "product": {
    "name": "OrbitID Enterprise",
    "version": "1.5.0",
    "type": "Корпоративная IdP-платформа",
    "description": "Платформа цифровой идентификации с авторизацией, двухфакторной аутентификацией и управлением профилями."
  },
  "documents": [
    {
      "id": "doc-301-1",
      "type": "спецификация требований",
      "title": "Спецификация требований",
      "summary": "Определяет обязательные сценарии авторизации и восстановления доступа.",
      "sections": [
        {
          "id": "doc-301-1-sec-1",
          "title": "Идентификация",
          "content": "Обозначение: STR-OID-ENT-1.5.0-2026. Версия релиза: 1.5.0. Сборка: OID-1.5.0.642.\nДата введения: 15.04.2026. Утверждено: директор по продукту И.А. Седых, 14.04.2026."
        },
        {
          "id": "doc-301-1-sec-2",
          "title": "Матрица обязательных сценариев",
          "content": "AUTH-01: успешная авторизация по логину и паролю.\nAUTH-02: блокировка после серии неуспешных попыток.\nAUTH-03: авторизация с включённой 2FA.\nAUTH-04: восстановление доступа по e-mail.\nAUTH-05: восстановление доступа по подтверждённому телефону.\nAUTH-06: смена пароля в профиле пользователя.\nAUTH-07: повторная авторизация после восстановления доступа."
        }
      ]
    },
    {
      "id": "doc-301-2",
      "type": "тест-план",
      "title": "Тест-план релиза",
      "summary": "Перечисляет сценарии проверки авторизации и профиля пользователя.",
      "sections": [
        {
          "id": "doc-301-2-sec-1",
          "title": "Идентификация",
          "content": "Обозначение: ТП-OID-ENT-1.5.0-2026. Версия релиза: 1.5.0. Сборка: OID-1.5.0.642.\nОснование: спецификация STR-OID-ENT-1.5.0-2026. Тестовый контур: UAT-ID-03."
        },
        {
          "id": "doc-301-2-sec-2",
          "title": "Предусловия",
          "content": "Шаблоны экранов профиля пользователя соответствуют редакции PF-24.04.\nСервис почтовых уведомлений и SMS-шлюз доступны из тестового контура."
        },
        {
          "id": "doc-301-2-sec-3",
          "title": "Сценарии проверки",
          "content": "AUTH-01, AUTH-02, AUTH-03, AUTH-04, AUTH-06 — высокий приоритет.\nPROF-01 (просмотр данных профиля), PROF-02 (смена телефона), PROF-03 (печать карточки) — средний и низкий приоритет.\nКритерии завершения: все сценарии высокого приоритета пройдены, критических дефектов нет."
        }
      ]
    },
    {
      "id": "doc-301-3",
      "type": "отчет о тестировании",
      "title": "Отчёт о тестировании",
      "summary": "Подтверждает выполнение сценариев из тест-плана.",
      "sections": [
        {
          "id": "doc-301-3-sec-1",
          "title": "Идентификация",
          "content": "Обозначение: ОТ-OID-ENT-1.5.0-2026. Версия релиза: 1.5.0. Сборка: OID-1.5.0.624.\nПериод: 16.04.2026–17.04.2026. Контур: UAT-ID-03.\nУтверждено: руководитель управления качества Н.П. Елагина, 18.04.2026."
        },
        {
          "id": "doc-301-3-sec-2",
          "title": "Результаты выполнения",
          "content": "AUTH-01 — пройден. AUTH-02 — пройден. AUTH-03 — пройден. AUTH-04 — пройден. AUTH-06 — пройден.\nPROF-01 — пройден. PROF-02 — пройден.\nPROF-03: печатная форма сформирована по шаблону PF-24.05."
        },
        {
          "id": "doc-301-3-sec-3",
          "title": "Вывод",
          "content": "Все сценарии тест-плана выполнены. Критических замечаний нет. Релиз рекомендован к передаче в промышленную эксплуатацию."
        }
      ]
    }
  ],
  "issues": [
    {
      "id": "issue-301-1",
      "title": "Тестирование проведено на сборке OID-1.5.0.624, а не OID-1.5.0.642",
      "description": "Спецификация и тест-план зафиксированы для сборки OID-1.5.0.642, однако отчёт о тестировании указывает сборку OID-1.5.0.624. Соответствие проверенной и выпускаемой сборки не подтверждено.",
      "relatedDocumentId": "doc-301-3",
      "severity": "high"
    },
    {
      "id": "issue-301-2",
      "title": "Шаблон профиля в отчёте не совпадает с предусловиями тест-плана",
      "description": "Предусловие тест-плана фиксирует редакцию PF-24.04, но результат PROF-03 в отчёте указывает шаблон PF-24.05. Тестирование проводилось на версии шаблона, не предусмотренной планом.",
      "relatedDocumentId": "doc-301-3",
      "severity": "medium"
    },
    {
      "id": "issue-301-3",
      "title": "Обязательный сценарий AUTH-05 не включён в тест-план и отчёт",
      "description": "Спецификация определяет AUTH-05 (восстановление доступа по подтверждённому телефону) как обязательный, однако он отсутствует и в тест-плане, и в отчёте о тестировании.",
      "relatedDocumentId": "doc-301-2",
      "severity": "medium"
    }
  ],
  "correctDecision": "reject",
  "explanation": "Отчёт составлен для другой сборки (624 вместо 642). Нельзя подтвердить, что именно выпускаемая версия прошла проверку. Дополнительно: обязательный сценарий AUTH-05 не проверялся.",
  "topics": ["идентификация сборки", "покрытие тест-плана", "прослеживаемость"]
}
